dj_utils/__init__.py
dj_utils/admin.py
dj_utils/cyclictask_core.py
dj_utils/file.py
dj_utils/http.py
dj_utils/image.py
dj_utils/modeltranslation.py
dj_utils/serializers.py
dj_utils/settings.py
dj_utils/tools.py
dj_utils/upload.py
dj_utils/validators.py
dj_utils/fields/__init__.py
dj_utils/fields/email.py
dj_utils/fields/o2o.py
dj_utils/fields/phone.py
dj_utils/forms/__init__.py
dj_utils/forms/bootstrap.py
dj_utils/forms/helpers.py
dj_utils/forms/modeltranslation.py
dj_utils/locale/en/LC_MESSAGES/django.mo
dj_utils/locale/en/LC_MESSAGES/django.po
dj_utils/locale/pl/LC_MESSAGES/django.mo
dj_utils/locale/pl/LC_MESSAGES/django.po
dj_utils/locale/ru/LC_MESSAGES/django.mo
dj_utils/locale/ru/LC_MESSAGES/django.po
dj_utils/locale/uk/LC_MESSAGES/django.mo
dj_utils/locale/uk/LC_MESSAGES/django.po
dj_utils/management/__init__.py
dj_utils/management/commands/__init__.py
dj_utils/management/commands/clear_old_tmp_uploaded_files.py
dj_utils/management/commands/dju_remake_thumbs.py
dj_utils/management/commands/dju_sqlcreateallindexes.py
dj_utils/management/commands/dju_sqldropallindexes.py
dj_utils/management/commands/run_cyclictask.py
dj_utils/static/bootstrap-3.3.1/css/bootstrap-theme.css
dj_utils/static/bootstrap-3.3.1/css/bootstrap-theme.css.map
dj_utils/static/bootstrap-3.3.1/css/bootstrap-theme.min.css
dj_utils/static/bootstrap-3.3.1/css/bootstrap.css
dj_utils/static/bootstrap-3.3.1/css/bootstrap.css.map
dj_utils/static/bootstrap-3.3.1/css/bootstrap.min.css
dj_utils/static/bootstrap-3.3.1/fonts/glyphicons-halflings-regular.eot
dj_utils/static/bootstrap-3.3.1/fonts/glyphicons-halflings-regular.svg
dj_utils/static/bootstrap-3.3.1/fonts/glyphicons-halflings-regular.ttf
dj_utils/static/bootstrap-3.3.1/fonts/glyphicons-halflings-regular.woff
dj_utils/static/bootstrap-3.3.1/js/bootstrap-filestyle.js
dj_utils/static/bootstrap-3.3.1/js/bootstrap.js
dj_utils/static/bootstrap-3.3.1/js/bootstrap.min.js
dj_utils-0.3.6.dist-info/DESCRIPTION.rst
dj_utils-0.3.6.dist-info/METADATA
dj_utils-0.3.6.dist-info/RECORD
dj_utils-0.3.6.dist-info/WHEEL
dj_utils-0.3.6.dist-info/metadata.json
dj_utils-0.3.6.dist-info/top_level.txt
