Metadata-Version: 2.0
Name: dj-utils
Version: 0.3.6
Summary: Django utilities.
Home-page: https://github.com/liminspace/dj-utils
Author: liminspace
Author-email: liminspace@gmail.com
License: BSD
Platform: UNKNOWN
Requires-Dist: django (>=1.9,<1.10)
Requires-Dist: simplejson
